DLAC/__init__.py
DLAC/anticheat.py
DLAC/parser.so
DLAC/scaler.gz
DLAC/models/bigger.onnx
DLAC/models/small.onnx
DLAC-0.0.3.dist-info/METADATA
DLAC-0.0.3.dist-info/WHEEL
DLAC-0.0.3.dist-info/top_level.txt
DLAC-0.0.3.dist-info/RECORD
