Metadata-Version: 2.1
Name: DLAC
Version: 0.0.3
Summary: Deep learning anti-cheat for CSGO
Home-page: UNKNOWN
Author: LaihoE
License: UNKNOWN
Platform: UNKNOWN
Requires-Dist: numpy (==1.21.5)
Requires-Dist: onnxruntime (==1.10.0)
Requires-Dist: pandas (==1.3.5)
Requires-Dist: scikit-learn (==1.0.1)
